{"data":[{"media_url":"https://scontent-iad3-1.cdninstagram.com/v/t51.29350-15/123999194_825340734676514_3732790600834906945_n.jpg?_nc_cat=110&ccb=1-7&_nc_sid=18de74&_nc_ohc=no_pSswYjoMQ7kNvgHXwbDG&_nc_ht=scontent-iad3-1.cdninstagram.com&edm=ANo9K5cEAAAA&oh=00_AYD-tZDMPPH-zK-eGxnCRLeeO9Tpw1ZYuLVTKI1tRwMvuQ&oe=669E29C8","permalink":"https://www.instagram.com/p/CHVGp13DD87/","id":"18077437267235513","github_media_url":"https://mdb.github.io/feeder/feeds/18077437267235513.jpg"},{"media_url":"https://scontent-iad3-2.cdninstagram.com/v/t51.29350-15/120074493_170921654577822_3342492238029337989_n.jpg?_nc_cat=109&ccb=1-7&_nc_sid=18de74&_nc_ohc=miDQkL-pKlYQ7kNvgFrv3DL&_nc_ht=scontent-iad3-2.cdninstagram.com&edm=ANo9K5cEAAAA&oh=00_AYA3_vAMql04tAm3d-byuqVJY_qLgmY9oAxEHFZ5iVOZLQ&oe=669E3D28","permalink":"https://www.instagram.com/p/CFjsQBkDbwn/","id":"18026909938287781","github_media_url":"https://mdb.github.io/feeder/feeds/18026909938287781.jpg"},{"media_url":"https://scontent-iad3-2.cdninstagram.com/v/t51.29350-15/118322314_369816180686680_3560023674999011444_n.jpg?_nc_cat=109&ccb=1-7&_nc_sid=18de74&_nc_ohc=urT2hgt4tkYQ7kNvgGvvFw8&_nc_ht=scontent-iad3-2.cdninstagram.com&edm=ANo9K5cEAAAA&oh=00_AYD_hv1lL-FAMsRf8s7zYh11HTx2PcLaNDA1cT6nAA5Oow&oe=669E3FCB","permalink":"https://www.instagram.com/p/CEbmnwBDYMR/","id":"17877193057798577","github_media_url":"https://mdb.github.io/feeder/feeds/17877193057798577.jpg"},{"media_url":"https://scontent-iad3-2.cdninstagram.com/v/t51.29350-15/117623119_2655072598066183_252916009243978529_n.jpg?_nc_cat=106&ccb=1-7&_nc_sid=18de74&_nc_ohc=kIG_LTtJd4oQ7kNvgH2DQxi&_nc_ht=scontent-iad3-2.cdninstagram.com&edm=ANo9K5cEAAAA&oh=00_AYDxCUdfs5GexJDn3y_QLHLSNV3m9hAwcPm_E-STSCXf7w&oe=669E340E","permalink":"https://www.instagram.com/p/CD3eSt_D2Ah/","id":"18156404035009815","github_media_url":"https://mdb.github.io/feeder/feeds/18156404035009815.jpg"},{"media_url":"https://scontent-iad3-2.cdninstagram.com/v/t51.29350-15/116425078_1520056481499392_825587508033446604_n.jpg?_nc_cat=103&ccb=1-7&_nc_sid=18de74&_nc_ohc=tiiji0FkCdkQ7kNvgFWtM59&_nc_ht=scontent-iad3-2.cdninstagram.com&edm=ANo9K5cEAAAA&oh=00_AYDNZPc_YiIF9aFOmtnYkHMCYWrQcyYccLnYhBIlK9q_0g&oe=669E4BAB","permalink":"https://www.instagram.com/p/CDOUDy5DIM7/","id":"17932123057395001","github_media_url":"https://mdb.github.io/feeder/feeds/17932123057395001.jpg"},{"media_url":"https://scontent-iad3-2.cdninstagram.com/v/t51.2885-15/101808683_259384778710893_5244042120609779877_n.jpg?_nc_cat=103&ccb=1-7&_nc_sid=18de74&_nc_ohc=J4KeEfrwdsIQ7kNvgE0Twdw&_nc_ht=scontent-iad3-2.cdninstagram.com&edm=ANo9K5cEAAAA&oh=00_AYD6FckGiYrx6h7lWDbQjUkI76tY6YwWmLVh_UgDnO35fA&oe=669E4D98","permalink":"https://www.instagram.com/p/CA7iPdCj6k-/","id":"17925352744392578","github_media_url":"https://mdb.github.io/feeder/feeds/17925352744392578.jpg"},{"media_url":"https://scontent-iad3-1.cdninstagram.com/v/t51.2885-15/91581916_530343554257135_2131023219765972418_n.jpg?_nc_cat=102&ccb=1-7&_nc_sid=18de74&_nc_ohc=Pq6GYFfr3OwQ7kNvgEqk2zi&_nc_ht=scontent-iad3-1.cdninstagram.com&edm=ANo9K5cEAAAA&oh=00_AYCOvJRA0zaOhdPS5EHaUpP5rNhBq1ARCHQvzmSUDaZ_ZA&oe=669E4BB0","permalink":"https://www.instagram.com/p/B-kJH1tD-6u/","id":"17878460944563038","github_media_url":"https://mdb.github.io/feeder/feeds/17878460944563038.jpg"},{"media_url":"https://scontent-iad3-2.cdninstagram.com/v/t51.2885-15/87824650_614452829121003_2662651314208034471_n.jpg?_nc_cat=103&ccb=1-7&_nc_sid=18de74&_nc_ohc=8-vZCNinJRsQ7kNvgGxt-z-&_nc_ht=scontent-iad3-2.cdninstagram.com&edm=ANo9K5cEAAAA&oh=00_AYDByDbgEE91Tlv-lAvPFvt9bniO1lXYRPI1L5lr9PRm5Q&oe=669E3DA2","permalink":"https://www.instagram.com/p/B9EcIJtjfnp/","id":"17867167030628972","github_media_url":"https://mdb.github.io/feeder/feeds/17867167030628972.jpg"},{"media_url":"https://scontent-iad3-2.cdninstagram.com/v/t51.2885-15/85116794_2559910507464804_6849868936745194876_n.jpg?_nc_cat=106&ccb=1-7&_nc_sid=18de74&_nc_ohc=rbisIceGY7YQ7kNvgEh72ix&_nc_ht=scontent-iad3-2.cdninstagram.com&edm=ANo9K5cEAAAA&oh=00_AYDbUn9tlFDXXDUnC-GIVn2DzGUTD5Pxc3pHHVvnJQiFng&oe=669E25D6","permalink":"https://www.instagram.com/p/B80954FjC1m/","id":"18093216253081761","github_media_url":"https://mdb.github.io/feeder/feeds/18093216253081761.jpg"},{"media_url":"https://scontent-iad3-2.cdninstagram.com/v/t51.2885-15/80722075_209201156774284_4522115000154866750_n.jpg?_nc_cat=111&ccb=1-7&_nc_sid=18de74&_nc_ohc=rV3QCewKuTcQ7kNvgGg3l1s&_nc_ht=scontent-iad3-2.cdninstagram.com&edm=ANo9K5cEAAAA&oh=00_AYAsdoFoedIwQv9-fCr7rGzMRFTM8VAOMfCTSZ8fen0VEw&oe=669E3A3C","permalink":"https://www.instagram.com/p/B7dfP8wjHjB/","id":"17862297553629883","github_media_url":"https://mdb.github.io/feeder/feeds/17862297553629883.jpg"},{"media_url":"https://scontent-iad3-2.cdninstagram.com/v/t51.2885-15/81626799_626813694730743_1128494610919377791_n.jpg?_nc_cat=105&ccb=1-7&_nc_sid=18de74&_nc_ohc=7ubY4cUc7pgQ7kNvgE46J22&_nc_ht=scontent-iad3-2.cdninstagram.com&edm=ANo9K5cEAAAA&oh=00_AYDP_5YPV7tLY9bWHaE3xuQneZTNOotJ5X-yMKDBFPZHhg&oe=669E3B7B","permalink":"https://www.instagram.com/p/B7Vr5zxDFcz/","id":"17895314491442729","github_media_url":"https://mdb.github.io/feeder/feeds/17895314491442729.jpg"},{"media_url":"https://scontent-iad3-2.cdninstagram.com/v/t51.2885-15/79602226_633509270737737_7140521292103094562_n.jpg?_nc_cat=100&ccb=1-7&_nc_sid=18de74&_nc_ohc=9ZBxr36gWcQQ7kNvgGf9zeU&_nc_ht=scontent-iad3-2.cdninstagram.com&edm=ANo9K5cEAAAA&oh=00_AYBtEe5oB1mAipieSlLQVOPRp75lOXNlxrQqJRst4UIhfw&oe=669E448F","permalink":"https://www.instagram.com/p/B7Dn_6PDUU_/","id":"17942565502309955","github_media_url":"https://mdb.github.io/feeder/feeds/17942565502309955.jpg"},{"media_url":"https://scontent-iad3-1.cdninstagram.com/v/t51.2885-15/75660177_1825425707602116_4915860519381839284_n.jpg?_nc_cat=108&ccb=1-7&_nc_sid=18de74&_nc_ohc=F14EfS6YrMwQ7kNvgFMeql6&_nc_ht=scontent-iad3-1.cdninstagram.com&edm=ANo9K5cEAAAA&oh=00_AYCPYXECrTUV8-GyUVyIXWk5KxKBuDayK_4YGqmZvszlwA&oe=669E315D","permalink":"https://www.instagram.com/p/B6LD3Xuj6y_/","id":"17849212960773620","github_media_url":"https://mdb.github.io/feeder/feeds/17849212960773620.jpg"},{"media_url":"https://scontent-iad3-2.cdninstagram.com/v/t51.2885-15/73537464_739631109891784_7345691301450063938_n.jpg?_nc_cat=111&ccb=1-7&_nc_sid=18de74&_nc_ohc=bOqVr3FibxIQ7kNvgGn7B-E&_nc_ht=scontent-iad3-2.cdninstagram.com&edm=ANo9K5cEAAAA&oh=00_AYBRfnCPZUFDfQIWxFpc30G7r6SoNiAF0yH7xfYsT1Whyw&oe=669E3BF3","permalink":"https://www.instagram.com/p/B5XnhJcju9l/","id":"18115147624060787","github_media_url":"https://mdb.github.io/feeder/feeds/18115147624060787.jpg"},{"media_url":"https://scontent-iad3-1.cdninstagram.com/v/t51.2885-15/70952731_459618417978407_1574811802383745983_n.jpg?_nc_cat=107&ccb=1-7&_nc_sid=18de74&_nc_ohc=hz99pZzKW1sQ7kNvgHVUHWO&_nc_ht=scontent-iad3-1.cdninstagram.com&edm=ANo9K5cEAAAA&oh=00_AYAPao81n2-ZCHbDAsg_MG89JBVVJSPHtLmGlMH8VKsjYA&oe=669E5654","permalink":"https://www.instagram.com/p/B3Wxq5dDBX3/","id":"17866553542503201","github_media_url":"https://mdb.github.io/feeder/feeds/17866553542503201.jpg"},{"media_url":"https://scontent-iad3-2.cdninstagram.com/v/t51.2885-15/69700089_121162765596834_7472289310382253878_n.jpg?_nc_cat=106&ccb=1-7&_nc_sid=18de74&_nc_ohc=JBwX02unXzQQ7kNvgHAHFsx&_nc_ht=scontent-iad3-2.cdninstagram.com&edm=ANo9K5cEAAAA&oh=00_AYBpNzpffCOtMdXZgliC3txySk_Z9BARzgv67zh1Z4xS7w&oe=669E4A6F","permalink":"https://www.instagram.com/p/B26RdsDDp4G/","id":"18053572723199316","github_media_url":"https://mdb.github.io/feeder/feeds/18053572723199316.jpg"},{"media_url":"https://scontent-iad3-2.cdninstagram.com/v/t51.2885-15/68951422_167227194423692_200352891503849866_n.jpg?_nc_cat=103&ccb=1-7&_nc_sid=18de74&_nc_ohc=M7Dw7WMa_GoQ7kNvgEU0Ou0&_nc_ht=scontent-iad3-2.cdninstagram.com&edm=ANo9K5cEAAAA&oh=00_AYAf9AjaZoSCpO30CtDHV8YQAKhY6bVPDl3TpHKgeMdrbg&oe=669E2E28","permalink":"https://www.instagram.com/p/B2gphpMD_Ht/","id":"17927068918315958","github_media_url":"https://mdb.github.io/feeder/feeds/17927068918315958.jpg"},{"media_url":"https://scontent-iad3-1.cdninstagram.com/v/t51.2885-15/69623146_152367822631392_2512251648800917657_n.jpg?_nc_cat=101&ccb=1-7&_nc_sid=18de74&_nc_ohc=SqtwQFnQS-YQ7kNvgFpiurA&_nc_ht=scontent-iad3-1.cdninstagram.com&edm=ANo9K5cEAAAA&oh=00_AYA57mgg8y7V_HHzh2f6ToMS4c5uKoQCXO0pyrJMb_855w&oe=669E4357","permalink":"https://www.instagram.com/p/B2WVXqAjoM1/","id":"17859361288512572","github_media_url":"https://mdb.github.io/feeder/feeds/17859361288512572.jpg"},{"media_url":"https://scontent-iad3-1.cdninstagram.com/v/t51.2885-15/70395022_357664591783189_7562069053920637387_n.jpg?_nc_cat=102&ccb=1-7&_nc_sid=18de74&_nc_ohc=1TcO-q6Ub0YQ7kNvgED98S2&_nc_ht=scontent-iad3-1.cdninstagram.com&edm=ANo9K5cEAAAA&oh=00_AYB9Pg8_miOF2JpPcr0u9VV566ID9SnoMqddGsZSfczvlw&oe=669E5629","permalink":"https://www.instagram.com/p/B2OshYxjTr7/","id":"17999884678262433","github_media_url":"https://mdb.github.io/feeder/feeds/17999884678262433.jpg"},{"media_url":"https://scontent-iad3-1.cdninstagram.com/v/t51.2885-15/68961684_163808128007772_6749270444590883463_n.jpg?_nc_cat=110&ccb=1-7&_nc_sid=18de74&_nc_ohc=-8eReF1p2jMQ7kNvgGuDqoG&_nc_ht=scontent-iad3-1.cdninstagram.com&edm=ANo9K5cEAAAA&oh=00_AYBEQwENeq-xaVwjdczCrlq_6w2nc47I9XuzFQWe7n0uyA&oe=669E2E23","permalink":"https://www.instagram.com/p/B2BwUfgDXAF/","id":"18013342816246860","github_media_url":"https://mdb.github.io/feeder/feeds/18013342816246860.jpg"},{"media_url":"https://scontent-iad3-1.cdninstagram.com/v/t51.2885-15/64666578_762497080813929_6009437467303562742_n.jpg?_nc_cat=104&ccb=1-7&_nc_sid=18de74&_nc_ohc=WUnPvOXM8Z4Q7kNvgERWOGC&_nc_ht=scontent-iad3-1.cdninstagram.com&edm=ANo9K5cEAAAA&oh=00_AYAtH-H2ukXtTEVbQuA0eXdhSEtDWndX0lu7C580YlmHpQ&oe=669E56A5","permalink":"https://www.instagram.com/p/BzQEzL_DA29/","id":"18059102449115466","github_media_url":"https://mdb.github.io/feeder/feeds/18059102449115466.jpg"},{"media_url":"https://scontent-iad3-1.cdninstagram.com/v/t51.2885-15/64841142_670690516692422_5786850100012947487_n.jpg?_nc_cat=102&ccb=1-7&_nc_sid=18de74&_nc_ohc=Gc0xlXFIRpQQ7kNvgHFocsp&_nc_ht=scontent-iad3-1.cdninstagram.com&edm=ANo9K5cEAAAA&oh=00_AYDW21sb-SXrHvnJt81gTJSWsNXCruKep_y7KTndaQ1ViQ&oe=669E2F86","permalink":"https://www.instagram.com/p/By-Bq7Sjviv/","id":"18060176482107540","github_media_url":"https://mdb.github.io/feeder/feeds/18060176482107540.jpg"},{"media_url":"https://scontent-iad3-2.cdninstagram.com/v/t51.2885-15/62074517_897829400558463_6559986730757239792_n.jpg?_nc_cat=106&ccb=1-7&_nc_sid=18de74&_nc_ohc=B2DtMQgVodIQ7kNvgEQgbrf&_nc_ht=scontent-iad3-2.cdninstagram.com&edm=ANo9K5cEAAAA&oh=00_AYA2HpxnYaqoUkzPK8s2I3vBxfR5FikjpuFJesKpx5ouyg&oe=669E4C79","permalink":"https://www.instagram.com/p/By7lm9yDtRB/","id":"18043182688150312","github_media_url":"https://mdb.github.io/feeder/feeds/18043182688150312.jpg"},{"media_url":"https://scontent-iad3-1.cdninstagram.com/v/t51.2885-15/60896058_815767075465325_5730242387883961124_n.jpg?_nc_cat=110&ccb=1-7&_nc_sid=18de74&_nc_ohc=MED6UstlWiEQ7kNvgGIxwfU&_nc_ht=scontent-iad3-1.cdninstagram.com&edm=ANo9K5cEAAAA&oh=00_AYCiJSs0RnwYeT24dk9A_ZhGkJM8N67Cbeau7Pr53BTy1g&oe=669E29E8","permalink":"https://www.instagram.com/p/ByPpxGFDwFH/","id":"18038778178150172","github_media_url":"https://mdb.github.io/feeder/feeds/18038778178150172.jpg"},{"media_url":"https://scontent-iad3-1.cdninstagram.com/v/t51.2885-15/59556237_119679199238487_6708686133431747419_n.jpg?_nc_cat=110&ccb=1-7&_nc_sid=18de74&_nc_ohc=IK2U9G-acyEQ7kNvgGIc4zA&_nc_ht=scontent-iad3-1.cdninstagram.com&edm=ANo9K5cEAAAA&oh=00_AYA-0W_USDHsPfYrhuW-YCY6LPl_mRzws22brZLTZQXSfA&oe=669E240B","permalink":"https://www.instagram.com/p/Bxw2KZFDCSA/","id":"17866779352387086","github_media_url":"https://mdb.github.io/feeder/feeds/17866779352387086.jpg"}],"paging":{"cursors":{"before":"QVFIUkRYTmM2RkJSb0otdEhuT3VWaDFfV1NtM3ZAlaW80NUc3WDhWc3o2UlFXWWIyOUc4ZA21qd0c4YnJNdTdNZAFUyamRZAdkpDbXh1TnJ2b1FxWVI0c0huQWln","after":"QVFIUmdadnBtUFdvcXk1bl9CWGZA2aDNUOTJhYTlBZAjBYbmRkQ3JUOXZAKdjZAfZAjlIOEtERWU4c1ZAjWUFzeHFNYktJbEZArM3ZA2RmtiRVJBNlB4LW5ienRCaXFB"},"next":"https://mdb.github.io/feeder/feeds/instagram-media-3.json"}}