{"data":[{"media_url":"https://scontent-iad3-2.cdninstagram.com/v/t51.29350-15/271552137_439544974322436_944900467020004541_n.jpg?_nc_cat=103&ccb=1-7&_nc_sid=c4dd86&_nc_ohc=_UKiEv2kB_kAX9kENin&_nc_ht=scontent-iad3-2.cdninstagram.com&edm=ANo9K5cEAAAA&oh=00_AfAuxyhAx7JgFxcdjzj6cUAOF6_H4wXZqjaat6BA7dyJCg&oe=65881788","permalink":"https://www.instagram.com/p/CYlsVEhrPzO/","id":"17918271800068403","github_media_url":"https://mdb.github.io/feeder/feeds/17918271800068403.jpg"},{"media_url":"https://scontent-iad3-1.cdninstagram.com/v/t51.29350-15/270043030_677093107031691_5908777618154774945_n.jpg?_nc_cat=101&ccb=1-7&_nc_sid=c4dd86&_nc_ohc=7PTly_oNlAoAX_70ox_&_nc_ht=scontent-iad3-1.cdninstagram.com&edm=ANo9K5cEAAAA&oh=00_AfDEc6E6Ma3dz0okGKKYR1VfK98fnKle0t-RrLKIvPBSLA&oe=6587B54A","permalink":"https://www.instagram.com/p/CX_IMDaLNWr/","id":"17876990258546030","github_media_url":"https://mdb.github.io/feeder/feeds/17876990258546030.jpg"},{"media_url":"https://scontent-iad3-1.cdninstagram.com/v/t51.29350-15/269609095_2292562024220282_6180767688996106349_n.jpg?_nc_cat=107&ccb=1-7&_nc_sid=c4dd86&_nc_ohc=0NsCKGxI6yUAX9uUE_M&_nc_ht=scontent-iad3-1.cdninstagram.com&edm=ANo9K5cEAAAA&oh=00_AfAbHrcC2CbGMp3h3BsA0OJAmIHYIp12SeSgwL0FyCMScw&oe=65891F37","permalink":"https://www.instagram.com/p/CXvle29Lgm2/","id":"17934037684862012","github_media_url":"https://mdb.github.io/feeder/feeds/17934037684862012.jpg"},{"media_url":"https://scontent-iad3-1.cdninstagram.com/v/t51.29350-15/268374517_487268769392988_2927544699524792332_n.jpg?_nc_cat=104&ccb=1-7&_nc_sid=c4dd86&_nc_ohc=TETCrqotby8AX8titoo&_nc_ht=scontent-iad3-1.cdninstagram.com&edm=ANo9K5cEAAAA&oh=00_AfAzEc-9kIsKJI2b3n8bCE4ZhfIceHc1lO_CUApwlJCg2A&oe=65878EDB","permalink":"https://www.instagram.com/p/CXn4dYqrGNP/","id":"17922635516041878","github_media_url":"https://mdb.github.io/feeder/feeds/17922635516041878.jpg"},{"media_url":"https://scontent-iad3-1.cdninstagram.com/v/t51.29350-15/261871846_1273338279759321_2224109693525736398_n.jpg?_nc_cat=107&ccb=1-7&_nc_sid=c4dd86&_nc_ohc=utYtJYClnlwAX_HDnlj&_nc_ht=scontent-iad3-1.cdninstagram.com&edm=ANo9K5cEAAAA&oh=00_AfDi_l4ned2prjZ6vYYFxoXPSYaFsLe7tT1JZiOGmNMpcw&oe=658816BD","permalink":"https://www.instagram.com/p/CW28EHvLQ_C/","id":"17860616111619760","github_media_url":"https://mdb.github.io/feeder/feeds/17860616111619760.jpg"},{"media_url":"https://scontent-iad3-1.cdninstagram.com/v/t51.29350-15/249018899_595372371590583_2145953663211736676_n.jpg?_nc_cat=101&ccb=1-7&_nc_sid=c4dd86&_nc_ohc=Z2msnRBrDGsAX9XBJh6&_nc_ht=scontent-iad3-1.cdninstagram.com&edm=ANo9K5cEAAAA&oh=00_AfBzHvkx1jGp-Y2soLzdE8pS5LLpuSGcrHaZ8NL0FlAmuw&oe=6589692D","permalink":"https://www.instagram.com/p/CVh5A1Cr5Ng/","id":"17946733120583859","github_media_url":"https://mdb.github.io/feeder/feeds/17946733120583859.jpg"},{"media_url":"https://scontent-iad3-1.cdninstagram.com/v/t51.29350-15/243225611_3212648165635731_6329771391307895845_n.jpg?_nc_cat=107&ccb=1-7&_nc_sid=c4dd86&_nc_ohc=6s-My-h-8YQAX99Fryd&_nc_ht=scontent-iad3-1.cdninstagram.com&edm=ANo9K5cEAAAA&oh=00_AfDbEXdnuAL3ECn4CayARMVcQTCnE4_UUpoTXEqaS1aaqA&oe=658812B8","permalink":"https://www.instagram.com/p/CUcZ5e2LF0s/","id":"17903082029232265","github_media_url":"https://mdb.github.io/feeder/feeds/17903082029232265.jpg"},{"media_url":"https://scontent-iad3-2.cdninstagram.com/v/t51.29350-15/240038096_2955904847985893_1474468218900281288_n.jpg?_nc_cat=105&ccb=1-7&_nc_sid=c4dd86&_nc_ohc=AKha2rqJVeoAX8dOm73&_nc_ht=scontent-iad3-2.cdninstagram.com&edm=ANo9K5cEAAAA&oh=00_AfBsjIo6nxpewR-upaGr5pLOBy68cu2bqHuDAFAZbJkqVA&oe=6589156D","permalink":"https://www.instagram.com/p/CS6eX_3rQew/","id":"17870167172551795","github_media_url":"https://mdb.github.io/feeder/feeds/17870167172551795.jpg"},{"media_url":"https://scontent-iad3-2.cdninstagram.com/v/t51.29350-15/234415768_567574291264212_9174871016146199632_n.jpg?_nc_cat=111&ccb=1-7&_nc_sid=c4dd86&_nc_ohc=yNZxrdYdLcoAX-p06i7&_nc_ht=scontent-iad3-2.cdninstagram.com&edm=ANo9K5cEAAAA&oh=00_AfCcrumNGlTOiR4apz2zYw_HuptgXo-vNdvrsqkwFFLr4w&oe=6587E563","permalink":"https://www.instagram.com/p/CSbk73QLhP-/","id":"18246389701040751","github_media_url":"https://mdb.github.io/feeder/feeds/18246389701040751.jpg"},{"media_url":"https://scontent-iad3-2.cdninstagram.com/v/t51.29350-15/209006623_3694541140650461_8344136122327155209_n.jpg?_nc_cat=109&ccb=1-7&_nc_sid=c4dd86&_nc_ohc=k8d1pfDNYl0AX8Q44mC&_nc_ht=scontent-iad3-2.cdninstagram.com&edm=ANo9K5cEAAAA&oh=00_AfCi0CQy5r7Zc1JHwofJDRHSJpfcp58mqx2gS0_lSdTBZA&oe=6588CAC1","permalink":"https://www.instagram.com/p/CQs7R9Gjsef/","id":"17917946131764394","github_media_url":"https://mdb.github.io/feeder/feeds/17917946131764394.jpg"},{"media_url":"https://scontent-iad3-2.cdninstagram.com/v/t51.29350-15/207572701_326327619115985_8411032307020887888_n.jpg?_nc_cat=109&ccb=1-7&_nc_sid=c4dd86&_nc_ohc=8YMdeF35X8gAX-ThZb-&_nc_ht=scontent-iad3-2.cdninstagram.com&edm=ANo9K5cEAAAA&oh=00_AfCeFyADF0kkA30GxBzFpd0MLImkqa6syQJDQUAUTQWPig&oe=65891697","permalink":"https://www.instagram.com/p/CQf9YuJj2Rz/","id":"17860454657552303","github_media_url":"https://mdb.github.io/feeder/feeds/17860454657552303.jpg"},{"media_url":"https://scontent-iad3-1.cdninstagram.com/v/t51.29350-15/205971765_581845532798203_458682501727139954_n.jpg?_nc_cat=102&ccb=1-7&_nc_sid=c4dd86&_nc_ohc=2fZtLxhP5ZQAX9-7OJh&_nc_ht=scontent-iad3-1.cdninstagram.com&edm=ANo9K5cEAAAA&oh=00_AfD5Y3bquR6Ja17V3HIGS3YEtXj6syquFj6UIZvruJxRuA&oe=65884E5B","permalink":"https://www.instagram.com/p/CQdd2dLjBI3/","id":"17879029727329252","github_media_url":"https://mdb.github.io/feeder/feeds/17879029727329252.jpg"},{"media_url":"https://scontent-iad3-1.cdninstagram.com/v/t51.29350-15/190861826_302156754869467_8383975327819014430_n.jpg?_nc_cat=107&ccb=1-7&_nc_sid=c4dd86&_nc_ohc=kGcfAuCcL6kAX_JwuTl&_nc_ht=scontent-iad3-1.cdninstagram.com&edm=ANo9K5cEAAAA&oh=00_AfAYqQtgXl6z78UkmeDRX3ojCTITAFKzA1Nr3G5pe2vRIw&oe=65880108","permalink":"https://www.instagram.com/p/CPSxOtdDPq1/","id":"17931925558526317","github_media_url":"https://mdb.github.io/feeder/feeds/17931925558526317.jpg"},{"media_url":"https://scontent-iad3-1.cdninstagram.com/v/t51.29350-15/190013961_579754276748413_2860086819317992277_n.jpg?_nc_cat=101&ccb=1-7&_nc_sid=c4dd86&_nc_ohc=s-fpzrOYNwsAX9eyPKI&_nc_ht=scontent-iad3-1.cdninstagram.com&edm=ANo9K5cEAAAA&oh=00_AfDmaHhRp1wBQ13i3G2x3kuIeEeVkJgqWKuOyp_Z4TYbaA&oe=65882727","permalink":"https://www.instagram.com/p/CPQHn74DR_Q/","id":"17886842885241935","github_media_url":"https://mdb.github.io/feeder/feeds/17886842885241935.jpg"},{"media_url":"https://scontent-iad3-1.cdninstagram.com/v/t51.29350-15/188990853_1396352147430185_539682798959295721_n.jpg?_nc_cat=108&ccb=1-7&_nc_sid=c4dd86&_nc_ohc=Vmp--etDESIAX-o__uR&_nc_ht=scontent-iad3-1.cdninstagram.com&edm=ANo9K5cEAAAA&oh=00_AfBoRSMLvlYH9mlrgE-e-fAy-aeQhHVv_54-TOoNnMISdw&oe=6587C0B6","permalink":"https://www.instagram.com/p/CPK7SwMDmp2/","id":"17896751362973487","github_media_url":"https://mdb.github.io/feeder/feeds/17896751362973487.jpg"},{"media_url":"https://scontent-iad3-2.cdninstagram.com/v/t51.29350-15/182012938_458851521863482_3378816675324290278_n.jpg?_nc_cat=111&ccb=1-7&_nc_sid=c4dd86&_nc_ohc=8u_GE-4jxL8AX8iZo_U&_nc_ht=scontent-iad3-2.cdninstagram.com&edm=ANo9K5cEAAAA&oh=00_AfBKi_O-Lxe-YZmrzGws8PKE-VFp_StRLsHl3ZrMO6kcfA&oe=65890D9D","permalink":"https://www.instagram.com/p/COhxDhGjqLr/","id":"18079486267301041","github_media_url":"https://mdb.github.io/feeder/feeds/18079486267301041.jpg"},{"media_url":"https://scontent-iad3-2.cdninstagram.com/v/t51.29350-15/166770234_498651217837384_4300195068728532714_n.jpg?_nc_cat=109&ccb=1-7&_nc_sid=c4dd86&_nc_ohc=ktGl0d2WbOgAX9jteD4&_nc_ht=scontent-iad3-2.cdninstagram.com&edm=ANo9K5cEAAAA&oh=00_AfDke4qMiE9SeRn-1FQQka7upQwcMSDo5o4vNL0JxWvJjg&oe=65881315","permalink":"https://www.instagram.com/p/CNFOJr1jYs1/","id":"17880352523306106","github_media_url":"https://mdb.github.io/feeder/feeds/17880352523306106.jpg"},{"media_url":"https://scontent-iad3-2.cdninstagram.com/v/t51.29350-15/163654971_129186695817219_3709833990382056331_n.jpg?_nc_cat=109&ccb=1-7&_nc_sid=c4dd86&_nc_ohc=FlNEjMag4jYAX9ZeWXr&_nc_ht=scontent-iad3-2.cdninstagram.com&edm=ANo9K5cEAAAA&oh=00_AfCzsKQG2ztrbuJV17KK-dm3dC1t-9RhX02isn7VYq4lzQ&oe=6588B9B2","permalink":"https://www.instagram.com/p/CMzExBmDoxF/","id":"17925188731550223","github_media_url":"https://mdb.github.io/feeder/feeds/17925188731550223.jpg"},{"media_url":"https://scontent-iad3-1.cdninstagram.com/v/t51.29350-15/154991142_257125589246088_8564003365593140851_n.jpg?_nc_cat=110&ccb=1-7&_nc_sid=c4dd86&_nc_ohc=H1QVtZjtTgkAX81PILZ&_nc_ht=scontent-iad3-1.cdninstagram.com&edm=ANo9K5cEAAAA&oh=00_AfDFN5TzQqMfx7GOx4NTWHvno1bvtfIDmaOBClBzp2cJXA&oe=6588A43F","permalink":"https://www.instagram.com/p/CL6djaljGll/","id":"17906373322704200","github_media_url":"https://mdb.github.io/feeder/feeds/17906373322704200.jpg"},{"media_url":"https://scontent-iad3-1.cdninstagram.com/v/t51.29350-15/154789927_1018435308680443_1431274972923449226_n.jpg?_nc_cat=110&ccb=1-7&_nc_sid=c4dd86&_nc_ohc=E7RAsE3f7zwAX80fr98&_nc_ht=scontent-iad3-1.cdninstagram.com&edm=ANo9K5cEAAAA&oh=00_AfC0p1HEEYuekZwoERs0ZKPiAk33BVTYC3j2ugcQDmY62g&oe=658902A6","permalink":"https://www.instagram.com/p/CL4ANIFjgrX/","id":"17849232659524246","github_media_url":"https://mdb.github.io/feeder/feeds/17849232659524246.jpg"},{"media_url":"https://scontent-iad3-2.cdninstagram.com/v/t51.29350-15/134253966_393876191847339_8638552719160102487_n.jpg?_nc_cat=106&ccb=1-7&_nc_sid=c4dd86&_nc_ohc=HlbSTHvtEFkAX-t7i3g&_nc_ht=scontent-iad3-2.cdninstagram.com&edm=ANo9K5cEAAAA&oh=00_AfBZy41ff_2jm8azSGFOQdp3vfGfkue50tlcrJkuZUnaYQ&oe=65888D74","permalink":"https://www.instagram.com/p/CJdrcF5jydW/","id":"18063649564261982","github_media_url":"https://mdb.github.io/feeder/feeds/18063649564261982.jpg"},{"media_url":"https://scontent-iad3-2.cdninstagram.com/v/t51.29350-15/127196998_286013309500399_5827467201019053571_n.jpg?_nc_cat=105&ccb=1-7&_nc_sid=c4dd86&_nc_ohc=drw8O7Rnnn8AX_RbpO8&_nc_ht=scontent-iad3-2.cdninstagram.com&edm=ANo9K5cEAAAA&oh=00_AfD3uWw5XqBzTCoSE-c6NdtWRCpyqFE6rdcVXBTtCkkmnA&oe=6588843D","permalink":"https://www.instagram.com/p/CH-K6vRj36C/","id":"17857312238288057","github_media_url":"https://mdb.github.io/feeder/feeds/17857312238288057.jpg"},{"media_url":"https://scontent-iad3-1.cdninstagram.com/v/t51.29350-15/125487962_1227943967602322_4548521283418660606_n.jpg?_nc_cat=104&ccb=1-7&_nc_sid=c4dd86&_nc_ohc=pRUG-ZjN9x8AX8ypNnc&_nc_ht=scontent-iad3-1.cdninstagram.com&edm=ANo9K5cEAAAA&oh=00_AfCOaKa2od8VNDD_8cST_hEwLNYMv0dijaxS_MitwA-ukg&oe=65884905","permalink":"https://www.instagram.com/p/CHuynhwDhG_/","id":"17897638894642781","github_media_url":"https://mdb.github.io/feeder/feeds/17897638894642781.jpg"},{"media_url":"https://scontent-iad3-1.cdninstagram.com/v/t51.29350-15/123999194_825340734676514_3732790600834906945_n.jpg?_nc_cat=110&ccb=1-7&_nc_sid=c4dd86&_nc_ohc=C3oh7-8rdX8AX_bA94b&_nc_ht=scontent-iad3-1.cdninstagram.com&edm=ANo9K5cEAAAA&oh=00_AfA0i4TYNwWNqE_tAQTBnv2YPnXh7n-san8xKHBdg0aCRg&oe=65883588","permalink":"https://www.instagram.com/p/CHVGp13DD87/","id":"18077437267235513","github_media_url":"https://mdb.github.io/feeder/feeds/18077437267235513.jpg"},{"media_url":"https://scontent-iad3-2.cdninstagram.com/v/t51.29350-15/120074493_170921654577822_3342492238029337989_n.jpg?_nc_cat=109&ccb=1-7&_nc_sid=c4dd86&_nc_ohc=lGMCpoOfPo8AX-kxqA8&_nc_ht=scontent-iad3-2.cdninstagram.com&edm=ANo9K5cEAAAA&oh=00_AfAU3odRlqAd4Asrs9PMTIgxOkQFf4kJ_PQs_BY_9g_eYw&oe=65888128","permalink":"https://www.instagram.com/p/CFjsQBkDbwn/","id":"18026909938287781","github_media_url":"https://mdb.github.io/feeder/feeds/18026909938287781.jpg"}],"paging":{"cursors":{"before":"QVFIUlRleGNMTU55ZAE9YRUx3b084U1ZAESmxuQi12TXlQTFRhQXYwSXFqRDgybC1kVFVZANGNVVlJDZA0lBNGNBcjl3T21GWTJiUkhTWnFOelA2bE5YcndDQ3ZAn","after":"QVFIUjBCY2VsbFhxb3F3YkJMSTNTS19WZAmVybTFlMzhManZACZAGhOV1Y2QkpCelQ5bGpETXRxX01xMnZADdDJfU1hfQVV5bDZA6RGR6MVNpb3hiNTU0ZA0xuTUxR"},"next":"https://mdb.github.io/feeder/feeds/instagram-media-2.json"}}