{"data":[{"media_url":"https://scontent-iad3-1.cdninstagram.com/v/t51.29350-15/123999194_825340734676514_3732790600834906945_n.jpg?_nc_cat=110&ccb=1-7&_nc_sid=18de74&_nc_ohc=aZzM0rKq0TEQ7kNvgEkjUyx&_nc_ht=scontent-iad3-1.cdninstagram.com&edm=ANo9K5cEAAAA&_nc_gid=ACxQJSLrYmua5L8uiJqBHOk&oh=00_AYCT-KjJo7gmM4r97JpRuHqI9dHFYgzE8UiOkSi0YaTSYg&oe=670B9648","permalink":"https://www.instagram.com/p/CHVGp13DD87/","id":"18077437267235513","github_media_url":"https://mdb.github.io/feeder/feeds/18077437267235513.jpg"},{"media_url":"https://scontent-iad3-2.cdninstagram.com/v/t51.29350-15/120074493_170921654577822_3342492238029337989_n.jpg?_nc_cat=109&ccb=1-7&_nc_sid=18de74&_nc_ohc=AIyY5IWK_4wQ7kNvgHWqzq2&_nc_ht=scontent-iad3-2.cdninstagram.com&edm=ANo9K5cEAAAA&_nc_gid=ACxQJSLrYmua5L8uiJqBHOk&oh=00_AYCWKNkqLtIp5GI2TBxPU715mf-5TpGJivQrBfOJMS0rIQ&oe=670BA9A8","permalink":"https://www.instagram.com/p/CFjsQBkDbwn/","id":"18026909938287781","github_media_url":"https://mdb.github.io/feeder/feeds/18026909938287781.jpg"},{"media_url":"https://scontent-iad3-2.cdninstagram.com/v/t51.29350-15/118322314_369816180686680_3560023674999011444_n.jpg?_nc_cat=109&ccb=1-7&_nc_sid=18de74&_nc_ohc=f8Dvfr7e9dUQ7kNvgGb44BB&_nc_ht=scontent-iad3-2.cdninstagram.com&edm=ANo9K5cEAAAA&_nc_gid=ACxQJSLrYmua5L8uiJqBHOk&oh=00_AYANNjDSHxHMq0hXdG5JXmOLhAO21aUn3sWtApBq7gOaIQ&oe=670BAC4B","permalink":"https://www.instagram.com/p/CEbmnwBDYMR/","id":"17877193057798577","github_media_url":"https://mdb.github.io/feeder/feeds/17877193057798577.jpg"},{"media_url":"https://scontent-iad3-2.cdninstagram.com/v/t51.29350-15/117623119_2655072598066183_252916009243978529_n.jpg?_nc_cat=106&ccb=1-7&_nc_sid=18de74&_nc_ohc=arkIItG8UCQQ7kNvgGgPpfw&_nc_ht=scontent-iad3-2.cdninstagram.com&edm=ANo9K5cEAAAA&_nc_gid=ACxQJSLrYmua5L8uiJqBHOk&oh=00_AYBS18xqUKqXJCJ5G5jrA8bqDUFQLwx1hA-G9vytBG439Q&oe=670BA08E","permalink":"https://www.instagram.com/p/CD3eSt_D2Ah/","id":"18156404035009815","github_media_url":"https://mdb.github.io/feeder/feeds/18156404035009815.jpg"},{"media_url":"https://scontent-iad3-2.cdninstagram.com/v/t51.29350-15/116425078_1520056481499392_825587508033446604_n.jpg?_nc_cat=103&ccb=1-7&_nc_sid=18de74&_nc_ohc=-lOKvennTOAQ7kNvgFqqvoM&_nc_ht=scontent-iad3-2.cdninstagram.com&edm=ANo9K5cEAAAA&_nc_gid=ACxQJSLrYmua5L8uiJqBHOk&oh=00_AYDw6tvX7jcrzWldffAikJWo93GGzKeAjaE0glqRnJktGg&oe=670BB82B","permalink":"https://www.instagram.com/p/CDOUDy5DIM7/","id":"17932123057395001","github_media_url":"https://mdb.github.io/feeder/feeds/17932123057395001.jpg"},{"media_url":"https://scontent-iad3-2.cdninstagram.com/v/t51.2885-15/101808683_259384778710893_5244042120609779877_n.jpg?_nc_cat=103&ccb=1-7&_nc_sid=18de74&_nc_ohc=wGiD019pGTEQ7kNvgF5jwlN&_nc_ht=scontent-iad3-2.cdninstagram.com&edm=ANo9K5cEAAAA&oh=00_AYBsY8IU7lnErrglXXBo7MjLOcKEIhQrBErQbhENsOXYeQ&oe=670BBA18","permalink":"https://www.instagram.com/p/CA7iPdCj6k-/","id":"17925352744392578","github_media_url":"https://mdb.github.io/feeder/feeds/17925352744392578.jpg"},{"media_url":"https://scontent-iad3-1.cdninstagram.com/v/t51.2885-15/91581916_530343554257135_2131023219765972418_n.jpg?_nc_cat=102&ccb=1-7&_nc_sid=18de74&_nc_ohc=F2xzRGOfQ_0Q7kNvgGKZBi_&_nc_ht=scontent-iad3-1.cdninstagram.com&edm=ANo9K5cEAAAA&oh=00_AYD0QIo36kNZN6Hn0P0OhVq1-htCuaQjcHhT_lfO1F1azg&oe=670BB830","permalink":"https://www.instagram.com/p/B-kJH1tD-6u/","id":"17878460944563038","github_media_url":"https://mdb.github.io/feeder/feeds/17878460944563038.jpg"},{"media_url":"https://scontent-iad3-2.cdninstagram.com/v/t51.2885-15/87824650_614452829121003_2662651314208034471_n.jpg?_nc_cat=103&ccb=1-7&_nc_sid=18de74&_nc_ohc=Gz49on7Ww8IQ7kNvgEV0siL&_nc_ht=scontent-iad3-2.cdninstagram.com&edm=ANo9K5cEAAAA&oh=00_AYCot0JNL7qae_vJX1WHMqxXZTaF3oIdoLHbvLgIa3RyEw&oe=670BAA22","permalink":"https://www.instagram.com/p/B9EcIJtjfnp/","id":"17867167030628972","github_media_url":"https://mdb.github.io/feeder/feeds/17867167030628972.jpg"},{"media_url":"https://scontent-iad3-2.cdninstagram.com/v/t51.2885-15/85116794_2559910507464804_6849868936745194876_n.jpg?_nc_cat=106&ccb=1-7&_nc_sid=18de74&_nc_ohc=gg0WWNySw8gQ7kNvgFm87EY&_nc_ht=scontent-iad3-2.cdninstagram.com&edm=ANo9K5cEAAAA&oh=00_AYAymG2D0enM3ecNBFmwBXIVHET-aj9mz44iBi_2xLUdwg&oe=670B9256","permalink":"https://www.instagram.com/p/B80954FjC1m/","id":"18093216253081761","github_media_url":"https://mdb.github.io/feeder/feeds/18093216253081761.jpg"},{"media_url":"https://scontent-iad3-2.cdninstagram.com/v/t51.2885-15/80722075_209201156774284_4522115000154866750_n.jpg?_nc_cat=111&ccb=1-7&_nc_sid=18de74&_nc_ohc=qrmIwG5sF2EQ7kNvgEs2ShJ&_nc_ht=scontent-iad3-2.cdninstagram.com&edm=ANo9K5cEAAAA&oh=00_AYCuLv1jYwSOcHUT3ehAK09EeRygaA6T5zuQVrXbCIoGAA&oe=670BA6BC","permalink":"https://www.instagram.com/p/B7dfP8wjHjB/","id":"17862297553629883","github_media_url":"https://mdb.github.io/feeder/feeds/17862297553629883.jpg"},{"media_url":"https://scontent-iad3-2.cdninstagram.com/v/t51.2885-15/81626799_626813694730743_1128494610919377791_n.jpg?_nc_cat=105&ccb=1-7&_nc_sid=18de74&_nc_ohc=l5phAMODBOoQ7kNvgHO6_t7&_nc_ht=scontent-iad3-2.cdninstagram.com&edm=ANo9K5cEAAAA&oh=00_AYC0nOTLTOm8zSynQR6K881LjKp2nQrNwuV2sKXXQa0Ajg&oe=670BA7FB","permalink":"https://www.instagram.com/p/B7Vr5zxDFcz/","id":"17895314491442729","github_media_url":"https://mdb.github.io/feeder/feeds/17895314491442729.jpg"},{"media_url":"https://scontent-iad3-2.cdninstagram.com/v/t51.2885-15/79602226_633509270737737_7140521292103094562_n.jpg?_nc_cat=100&ccb=1-7&_nc_sid=18de74&_nc_ohc=QMM0c3_kD5YQ7kNvgEoOtAt&_nc_ht=scontent-iad3-2.cdninstagram.com&edm=ANo9K5cEAAAA&oh=00_AYCLtsv-97Rq2B-3R358lLtRWA7FLJ91WMmFtwj96sPibg&oe=670BB10F","permalink":"https://www.instagram.com/p/B7Dn_6PDUU_/","id":"17942565502309955","github_media_url":"https://mdb.github.io/feeder/feeds/17942565502309955.jpg"},{"media_url":"https://scontent-iad3-1.cdninstagram.com/v/t51.2885-15/75660177_1825425707602116_4915860519381839284_n.jpg?_nc_cat=108&ccb=1-7&_nc_sid=18de74&_nc_ohc=QYbJF3Ti2KcQ7kNvgEs9GX-&_nc_ht=scontent-iad3-1.cdninstagram.com&edm=ANo9K5cEAAAA&oh=00_AYBTGVr9Ft8zCEwOGeOCnJZhLz3a-2V6WD09CULeenBv-A&oe=670B9DDD","permalink":"https://www.instagram.com/p/B6LD3Xuj6y_/","id":"17849212960773620","github_media_url":"https://mdb.github.io/feeder/feeds/17849212960773620.jpg"},{"media_url":"https://scontent-iad3-2.cdninstagram.com/v/t51.2885-15/73537464_739631109891784_7345691301450063938_n.jpg?_nc_cat=111&ccb=1-7&_nc_sid=18de74&_nc_ohc=eELIFmbLmxIQ7kNvgEYBUSQ&_nc_ht=scontent-iad3-2.cdninstagram.com&edm=ANo9K5cEAAAA&oh=00_AYDSz04qCWFfPUi2_wsBdqy_engOBjGx0cWpzM3jX7r0oA&oe=670BA873","permalink":"https://www.instagram.com/p/B5XnhJcju9l/","id":"18115147624060787","github_media_url":"https://mdb.github.io/feeder/feeds/18115147624060787.jpg"},{"media_url":"https://scontent-iad3-1.cdninstagram.com/v/t51.2885-15/70952731_459618417978407_1574811802383745983_n.jpg?_nc_cat=107&ccb=1-7&_nc_sid=18de74&_nc_ohc=hijlnHHdhFgQ7kNvgEZqCvS&_nc_ht=scontent-iad3-1.cdninstagram.com&edm=ANo9K5cEAAAA&oh=00_AYBEgZNSIfpHSHggFgihjPz-wGxBnPbx06DnvNcOQErWIw&oe=670BC2D4","permalink":"https://www.instagram.com/p/B3Wxq5dDBX3/","id":"17866553542503201","github_media_url":"https://mdb.github.io/feeder/feeds/17866553542503201.jpg"},{"media_url":"https://scontent-iad3-2.cdninstagram.com/v/t51.2885-15/69700089_121162765596834_7472289310382253878_n.jpg?_nc_cat=106&ccb=1-7&_nc_sid=18de74&_nc_ohc=ppzpI8n7NQQQ7kNvgGgybTl&_nc_ht=scontent-iad3-2.cdninstagram.com&edm=ANo9K5cEAAAA&oh=00_AYA8zq2zOQP3wul3BSXbnVE98DspHPWFQ0fGkzajXmk6TQ&oe=670BB6EF","permalink":"https://www.instagram.com/p/B26RdsDDp4G/","id":"18053572723199316","github_media_url":"https://mdb.github.io/feeder/feeds/18053572723199316.jpg"},{"media_url":"https://scontent-iad3-2.cdninstagram.com/v/t51.2885-15/68951422_167227194423692_200352891503849866_n.jpg?_nc_cat=103&ccb=1-7&_nc_sid=18de74&_nc_ohc=eE0nSkYksOIQ7kNvgEhak_y&_nc_ht=scontent-iad3-2.cdninstagram.com&edm=ANo9K5cEAAAA&oh=00_AYCaATnzBQ5X-xMU6Em-6CJNmFp0c-zt2ZhS5EZiTTg2Ew&oe=670B9AA8","permalink":"https://www.instagram.com/p/B2gphpMD_Ht/","id":"17927068918315958","github_media_url":"https://mdb.github.io/feeder/feeds/17927068918315958.jpg"},{"media_url":"https://scontent-iad3-1.cdninstagram.com/v/t51.2885-15/69623146_152367822631392_2512251648800917657_n.jpg?_nc_cat=101&ccb=1-7&_nc_sid=18de74&_nc_ohc=GOmuL3scGAwQ7kNvgES_ay3&_nc_ht=scontent-iad3-1.cdninstagram.com&edm=ANo9K5cEAAAA&oh=00_AYDsEyb7WEYeBgtl7fGrashxdQTt2_ElVvkA0cZeWjNfOw&oe=670BAFD7","permalink":"https://www.instagram.com/p/B2WVXqAjoM1/","id":"17859361288512572","github_media_url":"https://mdb.github.io/feeder/feeds/17859361288512572.jpg"},{"media_url":"https://scontent-iad3-1.cdninstagram.com/v/t51.2885-15/70395022_357664591783189_7562069053920637387_n.jpg?_nc_cat=102&ccb=1-7&_nc_sid=18de74&_nc_ohc=07AyaKNXCGoQ7kNvgHumBVc&_nc_ht=scontent-iad3-1.cdninstagram.com&edm=ANo9K5cEAAAA&oh=00_AYC02b1j6J9GbegCut3diKfFYv7kO0DwZjF19LUweUWVaw&oe=670BC2A9","permalink":"https://www.instagram.com/p/B2OshYxjTr7/","id":"17999884678262433","github_media_url":"https://mdb.github.io/feeder/feeds/17999884678262433.jpg"},{"media_url":"https://scontent-iad3-1.cdninstagram.com/v/t51.2885-15/68961684_163808128007772_6749270444590883463_n.jpg?_nc_cat=110&ccb=1-7&_nc_sid=18de74&_nc_ohc=WcQyVC4IOj8Q7kNvgHyh3q0&_nc_ht=scontent-iad3-1.cdninstagram.com&edm=ANo9K5cEAAAA&oh=00_AYAeykcj0kQ7bvyZhQ4YrzB0auWVV5uwp3TM7FYTdxgCpw&oe=670B9AA3","permalink":"https://www.instagram.com/p/B2BwUfgDXAF/","id":"18013342816246860","github_media_url":"https://mdb.github.io/feeder/feeds/18013342816246860.jpg"},{"media_url":"https://scontent-iad3-1.cdninstagram.com/v/t51.2885-15/64666578_762497080813929_6009437467303562742_n.jpg?_nc_cat=104&ccb=1-7&_nc_sid=18de74&_nc_ohc=olj3mVxxytgQ7kNvgH5OBy7&_nc_ht=scontent-iad3-1.cdninstagram.com&edm=ANo9K5cEAAAA&oh=00_AYBpSeB8C1PvFXExMCNIW6IIvr6uSNex8BZ_EdGluViv_A&oe=670BC325","permalink":"https://www.instagram.com/p/BzQEzL_DA29/","id":"18059102449115466","github_media_url":"https://mdb.github.io/feeder/feeds/18059102449115466.jpg"},{"media_url":"https://scontent-iad3-1.cdninstagram.com/v/t51.2885-15/64841142_670690516692422_5786850100012947487_n.jpg?_nc_cat=102&ccb=1-7&_nc_sid=18de74&_nc_ohc=TW0jYRaauEIQ7kNvgFkYlyW&_nc_ht=scontent-iad3-1.cdninstagram.com&edm=ANo9K5cEAAAA&oh=00_AYDn2LsQQQaiC7ujT4zWDhkIIna6jabHa4yVbc1jHXyIUA&oe=670B9C06","permalink":"https://www.instagram.com/p/By-Bq7Sjviv/","id":"18060176482107540","github_media_url":"https://mdb.github.io/feeder/feeds/18060176482107540.jpg"},{"media_url":"https://scontent-iad3-2.cdninstagram.com/v/t51.2885-15/62074517_897829400558463_6559986730757239792_n.jpg?_nc_cat=106&ccb=1-7&_nc_sid=18de74&_nc_ohc=NB-EWzMYK60Q7kNvgHL0QHU&_nc_ht=scontent-iad3-2.cdninstagram.com&edm=ANo9K5cEAAAA&oh=00_AYDwtz9vsPQwn-A6rNLUWqeV5GxkdkH-e101-Tgr6pUC5w&oe=670BB8F9","permalink":"https://www.instagram.com/p/By7lm9yDtRB/","id":"18043182688150312","github_media_url":"https://mdb.github.io/feeder/feeds/18043182688150312.jpg"},{"media_url":"https://scontent-iad3-1.cdninstagram.com/v/t51.2885-15/60896058_815767075465325_5730242387883961124_n.jpg?_nc_cat=110&ccb=1-7&_nc_sid=18de74&_nc_ohc=acL7DaA06vQQ7kNvgG1ct0N&_nc_ht=scontent-iad3-1.cdninstagram.com&edm=ANo9K5cEAAAA&oh=00_AYD_SJ8dB547a5MfswF3z5krQ2_3biXexA6-bJhuNfiA0A&oe=670B9668","permalink":"https://www.instagram.com/p/ByPpxGFDwFH/","id":"18038778178150172","github_media_url":"https://mdb.github.io/feeder/feeds/18038778178150172.jpg"},{"media_url":"https://scontent-iad3-1.cdninstagram.com/v/t51.2885-15/59556237_119679199238487_6708686133431747419_n.jpg?_nc_cat=110&ccb=1-7&_nc_sid=18de74&_nc_ohc=zxqiVs510BMQ7kNvgHvEHd-&_nc_ht=scontent-iad3-1.cdninstagram.com&edm=ANo9K5cEAAAA&oh=00_AYApO_LKvXHk4FLxFqsjRsramVYhVm2IwhoIR7BkCCiGpw&oe=670B908B","permalink":"https://www.instagram.com/p/Bxw2KZFDCSA/","id":"17866779352387086","github_media_url":"https://mdb.github.io/feeder/feeds/17866779352387086.jpg"}],"paging":{"cursors":{"before":"QVFIUkRYTmM2RkJSb0otdEhuT3VWaDFfV1NtM3ZAlaW80NUc3WDhWc3o2UlFXWWIyOUc4ZA21qd0c4YnJNdTdNZAFUyamRZAdkpDbXh1TnJ2b1FxWVI0c0huQWln","after":"QVFIUmdadnBtUFdvcXk1bl9CWGZA2aDNUOTJhYTlBZAjBYbmRkQ3JUOXZAKdjZAfZAjlIOEtERWU4c1ZAjWUFzeHFNYktJbEZArM3ZA2RmtiRVJBNlB4LW5ienRCaXFB"},"next":"https://mdb.github.io/feeder/feeds/instagram-media-3.json"}}