{"data":[{"media_url":"https://scontent-iad3-1.cdninstagram.com/v/t51.2885-15/16228683_1092134304242997_7610567957000749056_n.jpg?_nc_cat=104&ccb=1-7&_nc_sid=18de74&_nc_ohc=24Ymf9SHDxIAX-Q8p2D&_nc_ht=scontent-iad3-1.cdninstagram.com&edm=ANo9K5cEAAAA&oh=00_AfCsDbxHPzVdoJ8WuKWRFH8iOJ7gVe2G6potuWM0cdtChA&oe=65D6FCFE","permalink":"https://www.instagram.com/p/BQIhsY6jag8/","id":"17871578656009781","github_media_url":"https://mdb.github.io/feeder/feeds/17871578656009781.jpg"},{"media_url":"https://scontent-iad3-2.cdninstagram.com/v/t51.2885-15/16124271_925515987583624_361394894930968576_n.jpg?_nc_cat=109&ccb=1-7&_nc_sid=18de74&_nc_ohc=noHNopnUAowAX-n7YId&_nc_ht=scontent-iad3-2.cdninstagram.com&edm=ANo9K5cEAAAA&oh=00_AfD2fJ30LBmNLhL28VL3pOqgYkTeyduRobcGBIGgijwYwg&oe=65D68581","permalink":"https://www.instagram.com/p/BPsJbAKDZ9S/","id":"17859752776113831","github_media_url":"https://mdb.github.io/feeder/feeds/17859752776113831.jpg"},{"media_url":"https://scontent-iad3-2.cdninstagram.com/v/t51.2885-15/16110638_1391071167611147_5521860923561607168_n.jpg?_nc_cat=100&ccb=1-7&_nc_sid=18de74&_nc_ohc=I9iAUYlALOsAX-LREwc&_nc_ht=scontent-iad3-2.cdninstagram.com&edm=ANo9K5cEAAAA&oh=00_AfBpwPBc0aaatZqmE4H_V8im5g3tczShThDdW4F19vkdTw&oe=65D58A38","permalink":"https://www.instagram.com/p/BPaEAgwDdlo/","id":"17847284227190075","github_media_url":"https://mdb.github.io/feeder/feeds/17847284227190075.jpg"},{"media_url":"https://scontent-iad3-1.cdninstagram.com/v/t51.2885-15/16122380_231207213994955_776335142846201856_n.jpg?_nc_cat=104&ccb=1-7&_nc_sid=18de74&_nc_ohc=D_M97ZXgeGQAX8tNwOf&_nc_ht=scontent-iad3-1.cdninstagram.com&edm=ANo9K5cEAAAA&oh=00_AfDUfKhOsys74_fNp0ekYYmdM8jocm1sV0ID-qm5YceslA&oe=65D6A806","permalink":"https://www.instagram.com/p/BPU8noAjHGF/","id":"17847186277152700","github_media_url":"https://mdb.github.io/feeder/feeds/17847186277152700.jpg"},{"media_url":"https://scontent-iad3-2.cdninstagram.com/v/t51.2885-15/15802496_583517988514571_3466513957672452096_n.jpg?_nc_cat=100&ccb=1-7&_nc_sid=18de74&_nc_ohc=cDeCujnddTMAX9Cg0uR&_nc_ht=scontent-iad3-2.cdninstagram.com&edm=ANo9K5cEAAAA&oh=00_AfAAeZGuy5B4d-iqQuY2h3lEEtbZ6vt8ZWeNjeIMXRnwEA&oe=65D5BEDE","permalink":"https://www.instagram.com/p/BPIIi0LjVzn/","id":"17860243546076184","github_media_url":"https://mdb.github.io/feeder/feeds/17860243546076184.jpg"},{"media_url":"https://scontent-iad3-1.cdninstagram.com/v/t51.2885-15/14582258_1094957430626621_8191280086977085440_n.jpg?_nc_cat=110&ccb=1-7&_nc_sid=18de74&_nc_ohc=jL08SolQswAAX9nb7pb&_nc_ht=scontent-iad3-1.cdninstagram.com&edm=ANo9K5cEAAAA&oh=00_AfBHGoxgFLrE2fePy5FRq8GMSSaFMI9_y1h5msBiTII4-g&oe=65D71D7B","permalink":"https://www.instagram.com/p/BPH7rIiDSbm/","id":"17846861155152268","github_media_url":"https://mdb.github.io/feeder/feeds/17846861155152268.jpg"},{"media_url":"https://scontent-iad3-1.cdninstagram.com/v/t51.2885-15/15877404_702088549954590_5255579290581336064_n.jpg?_nc_cat=110&ccb=1-7&_nc_sid=18de74&_nc_ohc=5aG9x7vmJsMAX_thihB&_nc_ht=scontent-iad3-1.cdninstagram.com&edm=ANo9K5cEAAAA&oh=00_AfBKQ5MGkAe49cbb2xJVL3vCBFY5j_diHT2aSNeBlFZQwg&oe=65D62ED5","permalink":"https://www.instagram.com/p/BPC7DCFjvNn/","id":"17846806051157517","github_media_url":"https://mdb.github.io/feeder/feeds/17846806051157517.jpg"},{"media_url":"https://scontent-iad3-1.cdninstagram.com/v/t51.2885-15/15623941_172759483204729_4059895523912450048_n.jpg?_nc_cat=104&ccb=1-7&_nc_sid=18de74&_nc_ohc=8BuFA3DGi1QAX-2Pslq&_nc_ht=scontent-iad3-1.cdninstagram.com&edm=ANo9K5cEAAAA&oh=00_AfDzQLO0trPPFJoLRSqD7y2p56mlLDy0zW27qD0ov-MRbw&oe=65D71E6A","permalink":"https://www.instagram.com/p/BO7EisQjzhR/","id":"17868715618038179","github_media_url":"https://mdb.github.io/feeder/feeds/17868715618038179.jpg"},{"media_url":"https://scontent-iad3-2.cdninstagram.com/v/t51.2885-15/14597236_1244333578955439_5281082475672502272_n.jpg?_nc_cat=105&ccb=1-7&_nc_sid=18de74&_nc_ohc=ZIyolZGwPFIAX9HwGUC&_nc_ht=scontent-iad3-2.cdninstagram.com&edm=ANo9K5cEAAAA&oh=00_AfAiIccb68ABhFALP6xVpuvRFw4lIlMZErFlD_6CnqROTw&oe=65D56B49","permalink":"https://www.instagram.com/p/BO23Q7EjNfs/","id":"17856801736081482","github_media_url":"https://mdb.github.io/feeder/feeds/17856801736081482.jpg"},{"media_url":"https://scontent-iad3-2.cdninstagram.com/v/t51.2885-15/15535299_1386602178048407_3269878410557521920_n.jpg?_nc_cat=109&ccb=1-7&_nc_sid=18de74&_nc_ohc=WeBzqksYuIoAX_6LayX&_nc_ht=scontent-iad3-2.cdninstagram.com&edm=ANo9K5cEAAAA&oh=00_AfAsUu1PCIxQleoQ498Uu1P5GMs6sOs_uR_FBBda18VhDQ&oe=65D70539","permalink":"https://www.instagram.com/p/BOfJ-4HDWFu/","id":"17868228775001540","github_media_url":"https://mdb.github.io/feeder/feeds/17868228775001540.jpg"},{"media_url":"https://scontent-iad3-2.cdninstagram.com/v/t51.2885-15/15624249_690154564481157_6907138354995789824_n.jpg?_nc_cat=103&ccb=1-7&_nc_sid=18de74&_nc_ohc=yCKKBy4VCy4AX_qnMlB&_nc_ht=scontent-iad3-2.cdninstagram.com&edm=ANo9K5cEAAAA&oh=00_AfAenSx3sw8tVK2i-Tv5jHNrTUcoBiMsQ38iDhbPUyuQuA&oe=65D5A567","permalink":"https://www.instagram.com/p/BOdRKP0DjkZ/","id":"17847011506136259","github_media_url":"https://mdb.github.io/feeder/feeds/17847011506136259.jpg"},{"media_url":"https://scontent-iad3-1.cdninstagram.com/v/t51.2885-15/15623818_1272723166106824_4703401849577799680_n.jpg?_nc_cat=104&ccb=1-7&_nc_sid=18de74&_nc_ohc=gwLJRxUOLHoAX-DMZb9&_nc_ht=scontent-iad3-1.cdninstagram.com&edm=ANo9K5cEAAAA&oh=00_AfB7coOOJ0hx54t1mR8MQWUlgPaULQXfIsVFXjMDQ5Sm6A&oe=65D611A9","permalink":"https://www.instagram.com/p/BOM11tRj6Ka/","id":"17867431246057139","github_media_url":"https://mdb.github.io/feeder/feeds/17867431246057139.jpg"},{"media_url":"https://scontent-iad3-2.cdninstagram.com/v/t51.2885-15/15338345_765513333608209_6468856222547181568_n.jpg?_nc_cat=105&ccb=1-7&_nc_sid=18de74&_nc_ohc=2JbTVDTrppUAX-Yu7QZ&_nc_ht=scontent-iad3-2.cdninstagram.com&edm=ANo9K5cEAAAA&oh=00_AfAOkmFG6P8gRROyA67OiB_JPZtlrPRM3_C25iwAVOWwTQ&oe=65D6F563","permalink":"https://www.instagram.com/p/BN_2E21jUHd/","id":"17856938824096336","github_media_url":"https://mdb.github.io/feeder/feeds/17856938824096336.jpg"},{"media_url":"https://scontent-iad3-1.cdninstagram.com/v/t51.2885-15/15535212_707486042761947_2493918497529135104_n.jpg?_nc_cat=108&ccb=1-7&_nc_sid=18de74&_nc_ohc=dQTP2SBMqnQAX-W2rh8&_nc_ht=scontent-iad3-1.cdninstagram.com&edm=ANo9K5cEAAAA&oh=00_AfDpurle1EBTb-mZwNe9QHoU1ID4xx9i77LhtqeqA8zsMA&oe=65D5B15E","permalink":"https://www.instagram.com/p/BN9L6oLjcpP/","id":"17845394515164135","github_media_url":"https://mdb.github.io/feeder/feeds/17845394515164135.jpg"},{"media_url":"https://scontent-iad3-2.cdninstagram.com/v/t51.2885-15/15253137_1251376058255402_1640386737786060800_n.jpg?_nc_cat=105&ccb=1-7&_nc_sid=18de74&_nc_ohc=9fp2r3C8tFUAX8YMoW3&_nc_ht=scontent-iad3-2.cdninstagram.com&edm=ANo9K5cEAAAA&oh=00_AfAdkwnccp9LGsmiODve6Ebqj18C0C5PhF3rkHL0KuUwXQ&oe=65D66F73","permalink":"https://www.instagram.com/p/BN6uScjjK_U/","id":"17866987663001356","github_media_url":"https://mdb.github.io/feeder/feeds/17866987663001356.jpg"},{"media_url":"https://scontent-iad3-1.cdninstagram.com/v/t51.2885-15/15403464_212795665838653_1529143129154781184_n.jpg?_nc_cat=102&ccb=1-7&_nc_sid=18de74&_nc_ohc=f7vcsrRW-TcAX8z1r0w&_nc_ht=scontent-iad3-1.cdninstagram.com&edm=ANo9K5cEAAAA&oh=00_AfDhKU8htNu1ROXd-vbtJtjBw9OHSWE0mjljFfLogmQbfQ&oe=65D6DF27","permalink":"https://www.instagram.com/p/BNy1Iq0jTte/","id":"17866893349052832","github_media_url":"https://mdb.github.io/feeder/feeds/17866893349052832.jpg"},{"media_url":"https://scontent-iad3-2.cdninstagram.com/v/t51.2885-15/15251597_1037292096381236_7999116326666764288_n.jpg?_nc_cat=103&ccb=1-7&_nc_sid=18de74&_nc_ohc=PGvptkluaAMAX_jJg2t&_nc_ht=scontent-iad3-2.cdninstagram.com&edm=ANo9K5cEAAAA&oh=00_AfBg4Dr95dVMzz42_j_MArDhFL8PbbAZqWD-kqpiHUNh_Q&oe=65D5D291","permalink":"https://www.instagram.com/p/BNueDsHD01A/","id":"17845201249177076","github_media_url":"https://mdb.github.io/feeder/feeds/17845201249177076.jpg"},{"media_url":"https://scontent-iad3-2.cdninstagram.com/o1/v/t16/f1/m84/C94BC0D644CA4AB6C482545CDF553DB5_video_dashinit.mp4?efg=eyJ2ZW5jb2RlX3RhZyI6InZ0c192b2RfdXJsZ2VuLmZlZWQudW5rbm93bi1DMy40ODAuZGFzaF9iYXNlbGluZV8xX3YxIn0&_nc_ht=scontent-iad3-2.cdninstagram.com&_nc_cat=104&vs=784384743485012_2763131441&_nc_vs=HBkcFQIYTGlnX2JhY2tmaWxsX3RpbWVsaW5lX3ZvZC9DOTRCQzBENjQ0Q0E0QUI2QzQ4MjU0NUNERjU1M0RCNV92aWRlb19kYXNoaW5pdC5tcDQVAALIAQAoABgAGwGIB3VzZV9vaWwBMRUAACbync3qzJLLAhUCKAJDMywXQEwx64UeuFIYEmRhc2hfYmFzZWxpbmVfMV92MREAdeoHAA%3D%3D&ccb=9-4&oh=00_AfAQcTS9ZCg4h7xa78rdQWB3Uw8LjWXQLwcb5zN0q_womA&oe=65D3033C&_nc_sid=1d576d&_nc_rid=ab7bff4c57","permalink":"https://www.instagram.com/p/BNeckA_jXyT/","id":"17866934092008609","github_media_url":"https://mdb.github.io/feeder/feeds/17866934092008609.jpg"},{"media_url":"https://scontent-iad3-1.cdninstagram.com/v/t51.2885-15/14574179_230310070731790_790790070029254656_n.jpg?_nc_cat=110&ccb=1-7&_nc_sid=18de74&_nc_ohc=4FmpV9drMr8AX9Pug8l&_nc_oc=AQkEdQJ8-ALl7hEx59lfb08MN2oLX3-3B45wnvbK6dT296FyfoB11e7OUfTkuQ3OHE0&_nc_ht=scontent-iad3-1.cdninstagram.com&edm=ANo9K5cEAAAA&oh=00_AfAF29ecZV6SS-V_fdnGYjN-hOXov2ENLgfuw6NIp6jOgw&oe=65D61510","permalink":"https://www.instagram.com/p/BNUMNzfDzPO/","id":"17844829114192494","github_media_url":"https://mdb.github.io/feeder/feeds/17844829114192494.jpg"},{"media_url":"https://scontent-iad3-2.cdninstagram.com/o1/v/t16/f1/m84/F34F763C23E8BF4BF79A342FF0C177BD_video_dashinit.mp4?efg=eyJ2ZW5jb2RlX3RhZyI6InZ0c192b2RfdXJsZ2VuLmZlZWQudW5rbm93bi1DMy43MjAuZGFzaF9iYXNlbGluZV8xX3YxIn0&_nc_ht=scontent-iad3-2.cdninstagram.com&_nc_cat=110&vs=849553853512237_3887404552&_nc_vs=HBksFQIYTGlnX2JhY2tmaWxsX3RpbWVsaW5lX3ZvZC9GMzRGNzYzQzIzRThCRjRCRjc5QTM0MkZGMEMxNzdCRF92aWRlb19kYXNoaW5pdC5tcDQVAALIAQAVAhg6cGFzc3Rocm91Z2hfZXZlcnN0b3JlL0dMQ081eGJGUEZWX1poWUJBSC1iWTNRdFFvMWRicGt3QUFBRhUCAsgBACgAGAAbAYgHdXNlX29pbAExFQAAJprWiNWo0OwHFQIoAkMzLBdAO06XjU%2FfOxgSZGFzaF9iYXNlbGluZV8xX3YxEQB16gcA&ccb=9-4&oh=00_AfBQs13z1lOcVeApcQj5D0_oo1OdXbfm0UoRwHEv6TtkWQ&oe=65D2C8ED&_nc_sid=1d576d&_nc_rid=615e7d0d5f","permalink":"https://www.instagram.com/p/BNP3bQZDr4F/","id":"17866368901004720","github_media_url":"https://mdb.github.io/feeder/feeds/17866368901004720.jpg"},{"media_url":"https://scontent-iad3-1.cdninstagram.com/v/t51.2885-15/15056671_185667878561249_3619021112412733440_n.jpg?_nc_cat=104&ccb=1-7&_nc_sid=18de74&_nc_ohc=m0gO7OSWUhkAX-VrkmA&_nc_ht=scontent-iad3-1.cdninstagram.com&edm=ANo9K5cEAAAA&oh=00_AfChBrCkMib5h6vCWhKAKfKuLYvxA0p57aEENLSFvNy9cw&oe=65D688C0","permalink":"https://www.instagram.com/p/BNMmLIjD-WC/","id":"17855860093106468","github_media_url":"https://mdb.github.io/feeder/feeds/17855860093106468.jpg"},{"media_url":"https://scontent-iad3-2.cdninstagram.com/v/t51.2885-15/15034648_1762245794100080_4761036913370988544_n.jpg?_nc_cat=100&ccb=1-7&_nc_sid=18de74&_nc_ohc=8a-Tm8ExCHgAX-W-8bo&_nc_ht=scontent-iad3-2.cdninstagram.com&edm=ANo9K5cEAAAA&oh=00_AfAGP3cOCSRArS5t6XYDmSd1bGMlBPwUAUgBBr9qIMJqxA&oe=65D62FED","permalink":"https://www.instagram.com/p/BMy5dq7jdSm/","id":"17868535339035815","github_media_url":"https://mdb.github.io/feeder/feeds/17868535339035815.jpg"},{"media_url":"https://scontent-iad3-1.cdninstagram.com/v/t51.2885-15/14566533_187447275046729_8023572299946917888_n.jpg?_nc_cat=110&ccb=1-7&_nc_sid=18de74&_nc_ohc=1rill0GuYBwAX_xRKWU&_nc_ht=scontent-iad3-1.cdninstagram.com&edm=ANo9K5cEAAAA&oh=00_AfDOpJPNHyjXvQlE0ROp5RU-LORf9R4dr-F_ve2KqGxZsA&oe=65D6884B","permalink":"https://www.instagram.com/p/BMjSA4ODY9o/","id":"17844111967152005","github_media_url":"https://mdb.github.io/feeder/feeds/17844111967152005.jpg"},{"media_url":"https://scontent-iad3-1.cdninstagram.com/v/t51.2885-15/14677152_577467245794790_887633177303056384_n.jpg?_nc_cat=107&ccb=1-7&_nc_sid=18de74&_nc_ohc=CoUGCp9UnWcAX90zU18&_nc_ht=scontent-iad3-1.cdninstagram.com&edm=ANo9K5cEAAAA&oh=00_AfBIi9BV0-0GCo76IzWVDQkpIv4__lTxfeq3hfw4BYseiw&oe=65D6B26F","permalink":"https://www.instagram.com/p/BMTt2HND3w5/","id":"17863982755039495","github_media_url":"https://mdb.github.io/feeder/feeds/17863982755039495.jpg"},{"media_url":"https://scontent-iad3-2.cdninstagram.com/v/t51.2885-15/14676558_308326856217263_8349587882813423616_n.jpg?_nc_cat=111&ccb=1-7&_nc_sid=18de74&_nc_ohc=DRAnmJmWwDEAX9dje0c&_nc_ht=scontent-iad3-2.cdninstagram.com&edm=ANo9K5cEAAAA&oh=00_AfDkSoViskuwhzeuMLAOuDr7Zv_YICY7EHlRiniwMhlfGw&oe=65D73BF3","permalink":"https://www.instagram.com/p/BMOhWLZDlC7/","id":"17853766996088089","github_media_url":"https://mdb.github.io/feeder/feeds/17853766996088089.jpg"}],"paging":{"cursors":{"before":"QVFIUjljVHpQT0NPcldRbFN1Y2NiT3VndmpRWVluaTM4aHduQWg5RDNkMkJXMldiNTFaVzZAITkl3YlNOZATBrdENSUkR5SzdUdTBkT2UxM0p3cUowZAmlneXZAR","after":"QVFIUmxWV0RuYkVzek9zNlNwSTRZAekl6a0FRSkNnMTJIc3R6NTFGN2I3T1E2UVUwXzJRYnNzdzE4MXVaeU1yU1lXV0xKeFZApOGR6RFdmNGd2OHRqa1B6WXNB"},"next":"https://mdb.github.io/feeder/feeds/instagram-media-9.json"}}